ColorsAndStyles
