Metadata-Version: 2.1
Name: ColorsAndStyles
Version: 0.0.2
Summary: A basic package that makes it easy to add color and styles to your terminal.
Author: QwertyQwerty
Author-email: personqwertyperson88@gmail.com
License: MIT
Keywords: color,style,ansi
Classifier: Development Status :: 5 - Production/Stable
Classifier: Intended Audience :: Developers
Classifier: License :: OSI Approved :: MIT License
Classifier: Programming Language :: Python :: 3
Classifier: Operating System :: Unix
Classifier: Operating System :: MacOS :: MacOS X
Classifier: Operating System :: Microsoft :: Windows
License-File: LICENSE.txt
